{ "columns":16,
 "image":"..\/..\/..\/rhysh-maps\/rhysh-extra.png",
 "imageheight":512,
 "imagewidth":512,
 "margin":0,
 "name":"rhysh-extra",
 "spacing":0,
 "tilecount":256,
 "tiledversion":"1.9.2",
 "tileheight":32,
 "tiles":[
        {
         "id":0,
         "properties":[
                {
                 "name":"type",
                 "type":"string",
                 "value":"LargeStatue"
                }]
        }, 
        {
         "id":1,
         "properties":[
                {
                 "name":"facing",
                 "type":"string",
                 "value":"West"
                }, 
                {
                 "name":"type",
                 "type":"string",
                 "value":"Door"
                }]
        }, 
        {
         "id":2,
         "properties":[
                {
                 "name":"facing",
                 "type":"string",
                 "value":"North"
                }, 
                {
                 "name":"type",
                 "type":"string",
                 "value":"Door"
                }]
        }, 
        {
         "id":3,
         "properties":[
                {
                 "name":"direction",
                 "type":"string",
                 "value":"Up"
                }, 
                {
                 "name":"type",
                 "type":"string",
                 "value":"Stairs"
                }]
        }, 
        {
         "id":4,
         "properties":[
                {
                 "name":"extent",
                 "type":"string",
                 "value":"ES"
                }, 
                {
                 "name":"type",
                 "type":"string",
                 "value":"Arches"
                }]
        }, 
        {
         "id":5,
         "properties":[
                {
                 "name":"extent",
                 "type":"string",
                 "value":"SW"
                }, 
                {
                 "name":"type",
                 "type":"string",
                 "value":"Arches"
                }]
        }, 
        {
         "id":6,
         "properties":[
                {
                 "name":"extent",
                 "type":"string",
                 "value":"SEW"
                }, 
                {
                 "name":"type",
                 "type":"string",
                 "value":"Arches"
                }]
        }, 
        {
         "id":7,
         "properties":[
                {
                 "name":"extent",
                 "type":"string",
                 "value":"NSW"
                }, 
                {
                 "name":"type",
                 "type":"string",
                 "value":"Arches"
                }]
        }, 
        {
         "id":8,
         "properties":[
                {
                 "name":"extent",
                 "type":"string",
                 "value":"NS"
                }, 
                {
                 "name":"type",
                 "type":"string",
                 "value":"Arches"
                }]
        }, 
        {
         "id":9,
         "properties":[
                {
                 "name":"extent",
                 "type":"string",
                 "value":"NESW"
                }, 
                {
                 "name":"type",
                 "type":"string",
                 "value":"Arches"
                }]
        }, 
        {
         "id":10,
         "properties":[
                {
                 "name":"type",
                 "type":"string",
                 "value":"LargePillar"
                }]
        }, 
        {
         "id":16,
         "properties":[
                {
                 "name":"type",
                 "type":"string",
                 "value":"Statue"
                }]
        }, 
        {
         "id":17,
         "properties":[
                {
                 "name":"facing",
                 "type":"string",
                 "value":"East"
                }, 
                {
                 "name":"type",
                 "type":"string",
                 "value":"Door"
                }]
        }, 
        {
         "id":18,
         "properties":[
                {
                 "name":"facing",
                 "type":"string",
                 "value":"South"
                }, 
                {
                 "name":"type",
                 "type":"string",
                 "value":"Door"
                }]
        }, 
        {
         "id":19,
         "properties":[
                {
                 "name":"direction",
                 "type":"string",
                 "value":"Down"
                }, 
                {
                 "name":"type",
                 "type":"string",
                 "value":"Stairs"
                }]
        }, 
        {
         "id":20,
         "properties":[
                {
                 "name":"extent",
                 "type":"string",
                 "value":"NE"
                }, 
                {
                 "name":"type",
                 "type":"string",
                 "value":"Arches"
                }]
        }, 
        {
         "id":21,
         "properties":[
                {
                 "name":"extent",
                 "type":"string",
                 "value":"NW"
                }, 
                {
                 "name":"type",
                 "type":"string",
                 "value":"Arches"
                }]
        }, 
        {
         "id":22,
         "properties":[
                {
                 "name":"extent",
                 "type":"string",
                 "value":"NES"
                }, 
                {
                 "name":"type",
                 "type":"string",
                 "value":"Arches"
                }]
        }, 
        {
         "id":23,
         "properties":[
                {
                 "name":"extent",
                 "type":"string",
                 "value":"NEW"
                }, 
                {
                 "name":"type",
                 "type":"string",
                 "value":"Arches"
                }]
        }, 
        {
         "id":24,
         "properties":[
                {
                 "name":"extent",
                 "type":"string",
                 "value":"EW"
                }, 
                {
                 "name":"type",
                 "type":"string",
                 "value":"Arches"
                }]
        }, 
        {
         "id":25,
         "properties":[
                {
                 "name":"type",
                 "type":"string",
                 "value":"Pillar"
                }]
        }, 
        {
         "id":26,
         "properties":[
                {
                 "name":"type",
                 "type":"string",
                 "value":"DeepPit"
                }]
        }, 
        {
         "id":36,
         "properties":[
                {
                 "name":"extent",
                 "type":"string",
                 "value":"ES"
                }, 
                {
                 "name":"type",
                 "type":"string",
                 "value":"Channel"
                }]
        }, 
        {
         "id":37,
         "properties":[
                {
                 "name":"extent",
                 "type":"string",
                 "value":"SW"
                }, 
                {
                 "name":"type",
                 "type":"string",
                 "value":"Channel"
                }]
        }, 
        {
         "id":38,
         "properties":[
                {
                 "name":"extent",
                 "type":"string",
                 "value":"SEW"
                }, 
                {
                 "name":"type",
                 "type":"string",
                 "value":"Channel"
                }]
        }, 
        {
         "id":39,
         "properties":[
                {
                 "name":"extent",
                 "type":"string",
                 "value":"NSW"
                }, 
                {
                 "name":"type",
                 "type":"string",
                 "value":"Channel"
                }]
        }, 
        {
         "id":40,
         "properties":[
                {
                 "name":"extent",
                 "type":"string",
                 "value":"NS"
                }, 
                {
                 "name":"type",
                 "type":"string",
                 "value":"Channel"
                }]
        }, 
        {
         "id":41,
         "properties":[
                {
                 "name":"extent",
                 "type":"string",
                 "value":"NESW"
                }, 
                {
                 "name":"type",
                 "type":"string",
                 "value":"Channel"
                }]
        }, 
        {
         "id":52,
         "properties":[
                {
                 "name":"extent",
                 "type":"string",
                 "value":"NE"
                }, 
                {
                 "name":"type",
                 "type":"string",
                 "value":"Channel"
                }]
        }, 
        {
         "id":53,
         "properties":[
                {
                 "name":"extent",
                 "type":"string",
                 "value":"NW"
                }, 
                {
                 "name":"type",
                 "type":"string",
                 "value":"Channel"
                }]
        }, 
        {
         "id":54,
         "properties":[
                {
                 "name":"extent",
                 "type":"string",
                 "value":"NES"
                }, 
                {
                 "name":"type",
                 "type":"string",
                 "value":"Channel"
                }]
        }, 
        {
         "id":55,
         "properties":[
                {
                 "name":"extent",
                 "type":"string",
                 "value":"NEW"
                }, 
                {
                 "name":"type",
                 "type":"string",
                 "value":"Channel"
                }]
        }, 
        {
         "id":56,
         "properties":[
                {
                 "name":"extent",
                 "type":"string",
                 "value":"EW"
                }, 
                {
                 "name":"type",
                 "type":"string",
                 "value":"Channel"
                }]
        }, 
        {
         "id":57,
         "properties":[
                {
                 "name":"type",
                 "type":"string",
                 "value":"Pit"
                }]
        }],
 "tilewidth":32,
 "type":"tileset",
 "version":"1.9"
}